klowd_server_ext/__init__.py
klowd_server_ext/_version.py
klowd_server_ext-0.3.0.data/data/share/jupyter/labextensions/klowd_server_ext/package.json
klowd_server_ext-0.3.0.data/data/share/jupyter/labextensions/klowd_server_ext/static/509.78a43cb9e4eda52af6bd.js
klowd_server_ext-0.3.0.data/data/share/jupyter/labextensions/klowd_server_ext/static/728.362061fcb29ed9005039.js
klowd_server_ext-0.3.0.data/data/share/jupyter/labextensions/klowd_server_ext/static/remoteEntry.0b95913aee9f3604e9f8.js
klowd_server_ext-0.3.0.data/data/share/jupyter/labextensions/klowd_server_ext/static/style.js
klowd_server_ext-0.3.0.data/data/share/jupyter/labextensions/klowd_server_ext/static/third-party-licenses.json
klowd_server_ext-0.3.0.data/data/share/jupyter/labextensions/klowd_server_ext/install.json
klowd_server_ext-0.3.0.dist-info/METADATA
klowd_server_ext-0.3.0.dist-info/WHEEL
klowd_server_ext-0.3.0.dist-info/licenses/LICENSE
klowd_server_ext-0.3.0.dist-info/RECORD
